prophet/__init__.py
prophet/diagnostics.py
prophet/forecaster.py
prophet/hdays.py
prophet/make_holidays.py
prophet/models.py
prophet/plot.py
prophet/serialize.py
prophet/utilities.py
prophet/stan_model/prophet_model.bin
prophet/stan_model/cmdstan-2.26.1/bin/diagnose.exe
prophet/stan_model/cmdstan-2.26.1/bin/print.exe
prophet/stan_model/cmdstan-2.26.1/bin/stanc.exe
prophet/stan_model/cmdstan-2.26.1/bin/stansummary.exe
prophet/stan_model/cmdstan-2.26.1/stan/lib/stan_math/lib/tbb/arena.d
prophet/stan_model/cmdstan-2.26.1/stan/lib/stan_math/lib/tbb/arena.o
prophet/stan_model/cmdstan-2.26.1/stan/lib/stan_math/lib/tbb/backend.d
prophet/stan_model/cmdstan-2.26.1/stan/lib/stan_math/lib/tbb/backend.o
prophet/stan_model/cmdstan-2.26.1/stan/lib/stan_math/lib/tbb/backref.d
prophet/stan_model/cmdstan-2.26.1/stan/lib/stan_math/lib/tbb/backref.o
prophet/stan_model/cmdstan-2.26.1/stan/lib/stan_math/lib/tbb/cache_aligned_allocator.d
prophet/stan_model/cmdstan-2.26.1/stan/lib/stan_math/lib/tbb/cache_aligned_allocator.o
prophet/stan_model/cmdstan-2.26.1/stan/lib/stan_math/lib/tbb/concurrent_hash_map.d
prophet/stan_model/cmdstan-2.26.1/stan/lib/stan_math/lib/tbb/concurrent_hash_map.o
prophet/stan_model/cmdstan-2.26.1/stan/lib/stan_math/lib/tbb/concurrent_monitor.d
prophet/stan_model/cmdstan-2.26.1/stan/lib/stan_math/lib/tbb/concurrent_monitor.o
prophet/stan_model/cmdstan-2.26.1/stan/lib/stan_math/lib/tbb/concurrent_queue.d
prophet/stan_model/cmdstan-2.26.1/stan/lib/stan_math/lib/tbb/concurrent_queue.o
prophet/stan_model/cmdstan-2.26.1/stan/lib/stan_math/lib/tbb/concurrent_queue_v2.d
prophet/stan_model/cmdstan-2.26.1/stan/lib/stan_math/lib/tbb/concurrent_queue_v2.o
prophet/stan_model/cmdstan-2.26.1/stan/lib/stan_math/lib/tbb/concurrent_vector.d
prophet/stan_model/cmdstan-2.26.1/stan/lib/stan_math/lib/tbb/concurrent_vector.o
prophet/stan_model/cmdstan-2.26.1/stan/lib/stan_math/lib/tbb/concurrent_vector_v2.d
prophet_prebuilt-1.0.2.dist-info/LICENSE
prophet_prebuilt-1.0.2.dist-info/METADATA
prophet_prebuilt-1.0.2.dist-info/WHEEL
prophet_prebuilt-1.0.2.dist-info/top_level.txt
prophet_prebuilt-1.0.2.dist-info/RECORD
